<background>
  <starttime>
    <year>2022</year>
    <month>06</month>
    <day>14</day>
    <hour>12</hour>
    <minute>00</minute>
    <second>00</second>
  </starttime>
<!-- This animation starts at midnight and last 12 hours long. -->
  <static>
    <duration>480.0</duration>
<!-- Paths to be adapted regarding where you saved the pictures. -->
    <file>/usr/share/backgrounds/3_01.jpg</file>
  </static>
  <transition>
    <duration>1320.0</duration>
    <from>/usr/share/backgrounds/3_01.jpg</from>
    <to>/usr/share/backgrounds/3_02.jpg</to>
  </transition>
  <static>
    <duration>300.0</duration>
    <file>/usr/share/backgrounds/3_02.jpg</file>
  </static>
  <transition>
    <duration>1500.0</duration>
    <from>/usr/share/backgrounds/3_02.jpg</from>
    <to>/usr/share/backgrounds/3_03.jpg</to>
  </transition>
  <static>
    <duration>480.0</duration>
    <file>/usr/share/backgrounds/3_03.jpg</file>
  </static>
  <transition>
    <duration>1320.0</duration>
    <from>/usr/share/backgrounds/3_03.jpg</from>
    <to>/usr/share/backgrounds/3_04.jpg</to>
  </transition>
  <static>
    <duration>300.0</duration>
    <file>/usr/share/backgrounds/3_04.jpg</file>
  </static>
  <transition>
    <duration>1500.0</duration>
    <from>/usr/share/backgrounds/3_04.jpg</from>
    <to>/usr/share/backgrounds/3_05.jpg</to>
  </transition>
  <static>
    <duration>480.0</duration>
    <file>/usr/share/backgrounds/3_05.jpg</file>
  </static>
  <transition>
    <duration>1320.0</duration>
    <from>/usr/share/backgrounds/3_05.jpg</from>
    <to>/usr/share/backgrounds/3_06.jpg</to>
  </transition>
  <static>
    <duration>300.0</duration>
    <file>/usr/share/backgrounds/3_06.jpg</file>
  </static>
  <transition>
    <duration>1500.0</duration>
    <from>/usr/share/backgrounds/3_06.jpg</from>
    <to>/usr/share/backgrounds/3_07.jpg</to>
  </transition>
  <static>
    <duration>480.0</duration>
    <file>/usr/share/backgrounds/3_07.jpg</file>
  </static>
  <transition>
    <duration>1320.0</duration>
    <from>/usr/share/backgrounds/3_07.jpg</from>
    <to>/usr/share/backgrounds/3_08.jpg</to>
  </transition>
  <static>
    <duration>300.0</duration>
    <file>/usr/share/backgrounds/3_08.jpg</file>
  </static>
  <transition>
    <duration>1500.0</duration>
    <from>/usr/share/backgrounds/3_08.jpg</from>
    <to>/usr/share/backgrounds/3_09.jpg</to>
  </transition>
  <static>
    <duration>480.0</duration>
    <file>/usr/share/backgrounds/3_09.jpg</file>
  </static>
  <transition>
    <duration>1320.0</duration>
    <from>/usr/share/backgrounds/3_09.jpg</from>
    <to>/usr/share/backgrounds/3_10.jpg</to>
  </transition>
  <static>
    <duration>300.0</duration>
    <file>/usr/share/backgrounds/3_10.jpg</file>
  </static>
  <transition>
    <duration>1500.0</duration>
    <from>/usr/share/backgrounds/3_10.jpg</from>
    <to>/usr/share/backgrounds/3_11.jpg</to>
  </transition>
  <static>
    <duration>480.0</duration>
    <file>/usr/share/backgrounds/3_11.jpg</file>
  </static>
  <transition>
    <duration>1320.0</duration>
    <from>/usr/share/backgrounds/3_11.jpg</from>
    <to>/usr/share/backgrounds/3_12.jpg</to>
  </transition>
  <static>
    <duration>150.0</duration>
    <file>/usr/share/backgrounds/3_12.jpg</file>
  </static>
  <transition>
    <duration>750.0</duration>
    <from>/usr/share/backgrounds/3_12.jpg</from>
    <to>/usr/share/backgrounds/3_13.jpg</to>
  </transition>
    <static>
    <duration>150.0</duration>
    <file>/usr/share/backgrounds/3_13.jpg</file>
  </static>
  <transition>
    <duration>750.0</duration>
    <from>/usr/share/backgrounds/3_13.jpg</from>
    <to>/usr/share/backgrounds/3_14.jpg</to>
  </transition>
  <static>
    <duration>480.0</duration>
    <file>/usr/share/backgrounds/3_14.jpg</file>
  </static>
  <transition>
    <duration>1320.0</duration>
    <from>/usr/share/backgrounds/3_14.jpg</from>
    <to>/usr/share/backgrounds/3_15.jpg</to>
  </transition>
  <static>
    <duration>300.0</duration>
    <file>/usr/share/backgrounds/3_15.jpg</file>
  </static>
  <transition>
    <duration>1500.0</duration>
    <from>/usr/share/backgrounds/3_15.jpg</from>
    <to>/usr/share/backgrounds/3_16.jpg</to>
  </transition>
  <static>
    <duration>480.0</duration>
    <file>/usr/share/backgrounds/3_16.jpg</file>
  </static>
  <transition>
    <duration>1320.0</duration>
    <from>/usr/share/backgrounds/3_16.jpg</from>
    <to>/usr/share/backgrounds/3_17.jpg</to>
  </transition>
  <static>
    <duration>300.0</duration>
    <file>/usr/share/backgrounds/3_17.jpg</file>
  </static>
  <transition>
    <duration>1500.0</duration>
    <from>/usr/share/backgrounds/3_17.jpg</from>
    <to>/usr/share/backgrounds/3_18.jpg</to>
  </transition>
  <static>
    <duration>480.0</duration>
    <file>/usr/share/backgrounds/3_18.jpg</file>
  </static>
  <transition>
    <duration>1320.0</duration>
    <from>/usr/share/backgrounds/3_18.jpg</from>
    <to>/usr/share/backgrounds/3_19.jpg</to>
  </transition>
  <static>
    <duration>300.0</duration>
    <file>/usr/share/backgrounds/3_19.jpg</file>
  </static>
  <transition>
    <duration>1500.0</duration>
    <from>/usr/share/backgrounds/3_19.jpg</from>
    <to>/usr/share/backgrounds/3_20.jpg</to>
  </transition>
  <static>
    <duration>480.0</duration>
    <file>/usr/share/backgrounds/3_20.jpg</file>
  </static>
  <transition>
    <duration>1320.0</duration>
    <from>/usr/share/backgrounds/3_20.jpg</from>
    <to>/usr/share/backgrounds/3_21.jpg</to>
  </transition>
  <static>
    <duration>300.0</duration>
    <file>/usr/share/backgrounds/3_21.jpg</file>
  </static>
  <transition>
    <duration>1500.0</duration>
    <from>/usr/share/backgrounds/3_21.jpg</from>
    <to>/usr/share/backgrounds/3_22.jpg</to>
  </transition>
    <static>
    <duration>480.0</duration>
    <file>/usr/share/backgrounds/3_22.jpg</file>
  </static>
  <transition>
    <duration>1320.0</duration>
    <from>/usr/share/backgrounds/3_22.jpg</from>
    <to>/usr/share/backgrounds/3_23.jpg</to>
  </transition>
    <static>
    <duration>300.0</duration>
    <file>/usr/share/backgrounds/3_23.jpg</file>
  </static>
  <transition>
    <duration>1500.0</duration>
    <from>/usr/share/backgrounds/3_23.jpg</from>
    <to>/usr/share/backgrounds/3_24.jpg</to>
  </transition>
    <static>
    <duration>480.0</duration>
    <file>/usr/share/backgrounds/3_24.jpg</file>
  </static>
  <transition>
    <duration>1320.0</duration>
    <from>/usr/share/backgrounds/3_24.jpg</from>
    <to>/usr/share/backgrounds/3_25.jpg</to>
  </transition>
    <static>
    <duration>300.0</duration>
    <file>/usr/share/backgrounds/3_25.jpg</file>
  </static>
  <transition>
    <duration>1500.0</duration>
    <from>/usr/share/backgrounds/3_25.jpg</from>
    <to>/usr/share/backgrounds/3_01.jpg</to>
  </transition>
</background>
